middel/__init__.py
middel-0.1.1.dist-info/LICENSE.txt
middel-0.1.1.dist-info/METADATA
middel-0.1.1.dist-info/WHEEL
middel-0.1.1.dist-info/entry_points.txt
middel-0.1.1.dist-info/top_level.txt
middel-0.1.1.dist-info/RECORD
