Metadata-Version: 2.1
Name: middel
Version: 0.1.1
Summary: Middle/Modern English Translator CLI - Written in Python.
Home-page: https://github.com/johnnystarr/middel
Author: Johnny Starr
License-File: LICENSE.txt
